{"rss": {"@xmlns:atom": "http://www.w3.org/2005/Atom", "@xmlns:ht": "https://trends.google.com.tw/trends/trendingsearches/daily", "@version": "2.0", "channel": {"title": "Daily Search Trends", "description": "Recent searches", "link": "https://trends.google.com.tw/trends/trendingsearches/daily?geo=TW", "atom:link": {"@href": "https://trends.google.com.tw/trends/trendingsearches/daily/rss?geo=TW", "@rel": "self", "@type": "application/rss+xml"}, "item": [{"title": "Teams", "ht:approx_traffic": "20,000+", "description": "Microsoft Teams", "link": "https://trends.google.com.tw/trends/trendingsearches/daily?geo=TW#Teams", "pubDate": "Thu, 21 Jul 2022 10:00:00 +0800", "ht:picture": "https://t3.gstatic.com/images?q=tbn:ANd9GcR5GGCLMeFsLtELj2ptRRDWY7GzuMNWfaM7fd2vbpBygEsRbnimIVqKJwNc810pQPTYUDpRU3Z4", "ht:picture_source": "科技新報 TechNews", "ht:news_item": [{"ht:news_item_title": "Microsoft Teams 大當機！Word、Office 網頁版等連帶受影響，服務 ...", "ht:news_item_snippet": "據DownDetector 網站稱，在美東時間晚上10 點左右、也就是台灣時間上午約10 點，有超過4,800 位用戶回報Microsoft Teams 當機無法使用，包括。微軟旗下Microsoft 365&nbsp;...", "ht:news_item_url": "https://technews.tw/2022/07/21/microsoft-teams-down-for-thousands-of-users/", "ht:news_item_source": "科技新報 TechNews"}, {"ht:news_item_title": "視訊軟體Teams無法使用！台日美澳爆災情微軟：正在搶修中", "ht:news_item_snippet": "微軟視訊會議軟體Microsoft Teams在台灣時間21日上午傳出無法使用的狀況，全球數千名用戶受到影響，包括台灣、日本、澳洲及美國。微軟稍早表示，這與內部儲存服務的連&nbsp;...", "ht:news_item_url": "https://www.ettoday.net/news/20220721/2299108.htm", "ht:news_item_source": "ETtoday"}]}, {"title": "捷運", "ht:approx_traffic": "20,000+", "description": "板南線, 北捷", "link": "https://trends.google.com.tw/trends/trendingsearches/daily?geo=TW#%E6%8D%B7%E9%81%8B", "pubDate": "Thu, 21 Jul 2022 09:00:00 +0800", "ht:picture": "https://t3.gstatic.com/images?q=tbn:ANd9GcRb1MK4EOI1Q1bJSzVWgGBf37bmqsRx7m5VCb7DWU2WwVgPMFj7DWZaQdvNUvctYukpDlf5bZRp", "ht:picture_source": "中央社即時新聞", "ht:news_item": [{"ht:news_item_title": "台北捷運板南線異常2.5小時上班通勤人潮擠滿捷運站【更新】", "ht:news_item_snippet": "（中央社記者陳昱婷台北21日電）今天上班尖峰時間，捷運板南線往南港方向列車卻走走停停，北捷說明，是因為府中站軌道電路訊號異常，加上江子翠站有列車煞車異常導致，目前&nbsp;...", "ht:news_item_url": "https://www.cna.com.tw/news/ahel/202207215002.aspx", "ht:news_item_source": "中央社即時新聞"}, {"ht:news_item_title": "北捷板南線兩列車異常已排除班距恢復正常營運", "ht:news_item_snippet": "台北捷運板南線府中站及江子翠站分別在早上6點56分、7點2分發生軌道電路、煞車異常，北捷啟動SOP，調整車次班距，9點30分已恢復全線正常班距、正常運行。", "ht:news_item_url": "https://udn.com/news/story/7266/6476659", "ht:news_item_source": "udn OOPS! 新鮮事"}]}, {"title": "坤輿掩埋場", "ht:approx_traffic": "5,000+", "description": "坤輿", "link": "https://trends.google.com.tw/trends/trendingsearches/daily?geo=TW#%E5%9D%A4%E8%BC%BF%E6%8E%A9%E5%9F%8B%E5%A0%B4", "pubDate": "Thu, 21 Jul 2022 11:00:00 +0800", "ht:picture": "https://t2.gstatic.com/images?q=tbn:ANd9GcRkIpRufXfLe2Chlgi8AjuEmyIbUC48cxWtFAz-QC3gLtHtv9oLizSyxXc7k-u7dMI-Gz5_snAm", "ht:picture_source": "Yahoo奇摩新聞", "ht:news_item": [{"ht:news_item_title": "夜襲！坤輿掩埋場爆流血衝突學生眼鏡碎裂、至少7人傷", "ht:news_item_snippet": "苗栗縣造橋鄉坤輿事業廢棄物掩埋場，業者今（21）日凌晨3點夜襲，為排除廠區門口的圍籬與水泥石塊進場，大動作出動怪手開挖，與前來抗議的自救會成員衝突一觸即發，&nbsp;...", "ht:news_item_url": "https://tw.news.yahoo.com/%E5%A4%9C%E8%A5%B2-%E5%9D%A4%E8%BC%BF%E6%8E%A9%E5%9F%8B%E5%A0%B4%E7%88%86%E6%B5%81%E8%A1%80%E8%A1%9D%E7%AA%81-%E5%AD%B8%E7%94%9F%E7%9C%BC%E9%8F%A1%E7%A2%8E%E8%A3%82-%E8%87%B3%E5%B0%917%E4%BA%BA%E5%82%B7-000150374.html", "ht:news_item_source": "Yahoo奇摩新聞"}, {"ht:news_item_title": "「坤輿掩埋場」凌晨爆流血抗爭7人送醫| ETtoday社會新聞| ETtoday ...", "ht:news_item_snippet": "苗栗縣造橋鄉坤輿事業廢棄物掩埋場，傳出今、明2天將試運轉，反坤輿自救會號召聲援，深夜聚集20多人阻擋大車進場，雙方從深夜對峙到凌晨3點，最後在場方動用怪手清理&nbsp;...", "ht:news_item_url": "https://www.ettoday.net/news/20220721/2298783.htm", "ht:news_item_source": "ETtoday"}]}, {"title": "邰智源", "ht:approx_traffic": "2,000+", "description": null, "link": "https://trends.google.com.tw/trends/trendingsearches/daily?geo=TW#%E9%82%B0%E6%99%BA%E6%BA%90", "pubDate": "Thu, 21 Jul 2022 10:00:00 +0800", "ht:picture": "https://t2.gstatic.com/images?q=tbn:ANd9GcS2aouKfaHve643o0dBZ23-Nho_NyD0g_0YRcQg7hLomoQgfrwuHbsSYZvHiQ9ZluO71WdF2a5k", "ht:picture_source": "Yahoo奇摩新聞", "ht:news_item": [{"ht:news_item_title": "邰智源29年前結婚片瘋傳！金城武來了舔共男星慘被消除", "ht:news_item_snippet": "主持人邰智源出道超過30年，早期以演短劇出道，最近他轉戰網路節目《木曜4超玩》再次受到年輕人喜愛走紅。而邰智源1993年與「連環泡」製作人妻子徐雅琪結婚，育有一子邰靖&nbsp;...", "ht:news_item_url": "https://tw.news.yahoo.com/%E9%82%B0%E6%99%BA%E6%BA%9029%E5%B9%B4%E5%89%8D%E7%B5%90%E5%A9%9A%E7%89%87%E7%98%8B%E5%82%B3-%E9%87%91%E5%9F%8E%E6%AD%A6%E4%BE%86%E4%BA%86-%E8%88%94%E5%85%B1%E7%94%B7%E6%98%9F%E6%85%98%E8%A2%AB%E5%89%8A%E9%99%A4-165504166.html", "ht:news_item_source": "Yahoo奇摩新聞"}, {"ht:news_item_title": "邰智源婚宴「超大咖陣容」網驚呼！ 金城武、陳松勇、庹宗康全到了", "ht:news_item_snippet": "邰智源在演藝圈發展31年，1993年娶知名製作人和廣播主持人徐雅琪時，婚禮還有《笑星撞地球》全程記錄，如今這段影片再被上傳到YouTube，網友被演算到後驚呼當年賓客真&nbsp;...", "ht:news_item_url": "https://star.ettoday.net/news/2298850", "ht:news_item_source": "ETtoday星光雲"}]}, {"title": "陳信安", "ht:approx_traffic": "2,000+", "description": null, "link": "https://trends.google.com.tw/trends/trendingsearches/daily?geo=TW#%E9%99%B3%E4%BF%A1%E5%AE%89", "pubDate": "Thu, 21 Jul 2022 00:00:00 +0800", "ht:picture": "https://t2.gstatic.com/images?q=tbn:ANd9GcTEY5qFmZve6x8Eh-S44lr6aaz-vNZwGYJhmNoJea_fzItmUBbP6Vy_PSpLlbuqUEgBvApT7Ifl", "ht:picture_source": "中央社即時新聞", "ht:news_item": [{"ht:news_item_title": "張鎮衙、陳范柏彥選秀狀元熱門陳信安親「驗貨」", "ht:news_item_snippet": "P. LEAGUE+ 在選秀會登場前，先辦新秀體能測試會，桃園領航猿總經理陳信安儘管退役多年，今天親自參加對抗賽，與新秀較勁，並對狀元熱門人選張鎮衙、陳范柏彥印象&nbsp;...", "ht:news_item_url": "https://www.cna.com.tw/news/aspt/202207200322.aspx", "ht:news_item_source": "中央社即時新聞"}, {"ht:news_item_title": "PLG／陳信安親自驗貨大讚張鎮衙、陳范柏彥身體素質佳", "ht:news_item_snippet": "PLG今天舉行選秀測試賽，並在最後一場賽事由陳信安、楊敬敏、王信凱等學長組隊迎戰待選球員組成「Hopefuls」，最終學...", "ht:news_item_url": "https://udn.com/news/story/7003/6475632", "ht:news_item_source": "UDN 聯合新聞網"}]}, {"title": "Pixel 6a", "ht:approx_traffic": "2,000+", "description": null, "link": "https://trends.google.com.tw/trends/trendingsearches/daily?geo=TW#Pixel%206a", "pubDate": "Thu, 21 Jul 2022 12:00:00 +0800", "ht:picture": "https://t3.gstatic.com/images?q=tbn:ANd9GcR7w-13NfqJLxISUQUjZfu5Z_ae3UTFuq1HAOfgQk5V1vH1LyfmmHRvq6moqIVe-I2E1TfMkevl", "ht:picture_source": "SOGI 手機王", "ht:news_item": [{"ht:news_item_title": "Google Pixel 6a與Pixel Buds Pro預購時間確定7/28台灣上市", "ht:news_item_snippet": "Google Pixel 6a 發表已有一段時間，先前Google 只宣布將於7 月開賣，不過稍早蝦皮商城Google 產品旗艦店搶先Google 官方商店預告台灣上市資訊。Google Pixel 6a 手機&nbsp;...", "ht:news_item_url": "https://www.sogi.com.tw/articles/google_pixel_6a/6258252", "ht:news_item_source": "SOGI 手機王"}, {"ht:news_item_title": "Pixel 6a開放預訂！專案價0元起電信資費曝", "ht:news_item_snippet": "記者谷庭／台北報導全新Google Pixel 6a手機及Pixel Buds Pro無線耳機，將於7月28日正式開賣，這次一樣由台灣大哥大為電信獨賣，今（21日）", "ht:news_item_url": "https://tw.news.yahoo.com/pixel-6a%E9%96%8B%E6%94%BE%E9%A0%90%E8%A8%82-%E5%B0%88%E6%A1%88%E5%83%B90%E5%85%83%E8%B5%B7-%E9%9B%BB%E4%BF%A1%E8%B3%87%E8%B2%BB%E6%9B%9D-023520814.html", "ht:news_item_source": "Yahoo奇摩新聞"}]}, {"title": "蔡阿嘎", "ht:approx_traffic": "2,000+", "description": null, "link": "https://trends.google.com.tw/trends/trendingsearches/daily?geo=TW#%E8%94%A1%E9%98%BF%E5%98%8E", "pubDate": "Thu, 21 Jul 2022 12:00:00 +0800", "ht:picture": "https://t0.gstatic.com/images?q=tbn:ANd9GcQvApN6WJiCU3RjllgT67KdtEO9nNV2htTE8-aCtdPfjuKMHVbwjakPl3k5exMNvb8yxG7XgLCB", "ht:picture_source": "Yahoo奇摩新聞", "ht:news_item": [{"ht:news_item_title": "賣房也要圓夢！蔡阿嘎生日拋震撼彈", "ht:news_item_snippet": "百萬YouTuber蔡阿嘎在台灣擁有超高知名度，他在昨（20）日宣布一項「重大決定」，即將成立社會福利協會，目前也已經送件處理，這也是前陣子賣房的原因，更是他深思熟慮&nbsp;...", "ht:news_item_url": "https://tw.news.yahoo.com/%E8%B3%A3%E6%88%BF%E4%B9%9F%E8%A6%81%E5%9C%93%E5%A4%A2-%E8%94%A1%E9%98%BF%E5%98%8E%E7%94%9F%E6%97%A5%E6%8B%8B%E9%9C%87%E6%92%BC%E5%BD%88-020607405.html", "ht:news_item_source": "Yahoo奇摩新聞"}, {"ht:news_item_title": "蔡阿嘎「重大宣布」拋震撼彈！ 38歲生日前夕圓夢：賣房也要完成", "ht:news_item_snippet": "百萬YouTuber蔡阿嘎以愛台灣形象打開知名度，近日剛完成歷時7天全台環島的他，昨（20日）又釋出一項「重大宣布」，決定成立社會福利協會，目前已經送件處理，&nbsp;...", "ht:news_item_url": "https://star.ettoday.net/news/2298793", "ht:news_item_source": "ETtoday星光雲"}]}, {"title": "費翔", "ht:approx_traffic": "2,000+", "description": null, "link": "https://trends.google.com.tw/trends/trendingsearches/daily?geo=TW#%E8%B2%BB%E7%BF%94", "pubDate": "Thu, 21 Jul 2022 12:00:00 +0800", "ht:picture": "https://t0.gstatic.com/images?q=tbn:ANd9GcRJNyfiwEBi93SCoaEjkW7gEXYx4kkGk1MceIUYxapJT-ZL8nb2hQyESJJ6AARtJpopXCPAQGaW", "ht:picture_source": "ETtoday星光雲", "ht:news_item": [{"ht:news_item_title": "費翔61歲近況曝光！揭倫敦日常「IP位置卻在上海」 聲明還原始末", "ht:news_item_snippet": "歌手費翔以演唱《冬天裡的一把火》走紅80年代，憑著俊俏臉龐和結實身材，一直是許多人心目中的不老男神。現年61歲的他，已經許久未現身公開場合，但仍不時會透過微博&nbsp;...", "ht:news_item_url": "https://star.ettoday.net/news/2298823", "ht:news_item_source": "ETtoday星光雲"}, {"ht:news_item_title": "費翔淡出多年罕曝61歲近況IP竟意外惹爭議", "ht:news_item_snippet": "華裔美籍混血男星費翔，擁有淺棕色的電眼和190公分的挺拔身材，加上影歌雙棲，曾在80年代紅極一時，更是少女們的白馬王子。今年61歲的費翔，已好多年未現身公開場合，&nbsp;...", "ht:news_item_url": "https://tw.news.yahoo.com/%E8%B2%BB%E7%BF%94%E6%B7%A1%E5%87%BA%E5%A4%9A%E5%B9%B4%E7%BD%95%E6%9B%9D61%E6%AD%B2%E8%BF%91%E6%B3%81-ip%E7%AB%9F%E6%84%8F%E5%A4%96%E6%83%B9%E7%88%AD%E8%AD%B0-161105197.html", "ht:news_item_source": "Yahoo奇摩新聞"}]}, {"title": "卓君澤", "ht:approx_traffic": "2,000+", "description": null, "link": "https://trends.google.com.tw/trends/trendingsearches/daily?geo=TW#%E5%8D%93%E5%90%9B%E6%BE%A4", "pubDate": "Thu, 21 Jul 2022 11:00:00 +0800", "ht:picture": "https://t3.gstatic.com/images?q=tbn:ANd9GcQEhPtTwXEBa0c0pa2qpMCV1lVKFscWkImO6iCbFg-eHWXB7CooFt_DUKRv_es-TbxLNoj07pmW", "ht:picture_source": "ETtoday星光雲", "ht:news_item": [{"ht:news_item_title": "卓君澤曝和威廉做「假日夫妻」不避孕：我們很努力", "ht:news_item_snippet": "《全明星運動會》第四季即將開播，今（20日）舉辦首映記者會，由專業國手錢薇娟、江宏傑、郭泓志帶領藍、紅、黃三隊揭開序幕。而接棒蔡尚樺賽事主播的卓君澤，&nbsp;...", "ht:news_item_url": "https://star.ettoday.net/news/2298665", "ht:news_item_source": "ETtoday星光雲"}, {"ht:news_item_title": "婚姻爆危機！威廉「驚人之舉」遭卓君澤大罵：你是想死嗎", "ht:news_item_snippet": "記者蔡維歆／台北報導節目為了爭奪天堂般的饗宴舉辦「胴體炸裂美拍合作賽」，威廉高舉Dora的照片在IG上一PO出，網友一片好評，獲得最高票九千多個讚，連坤達都到底下&nbsp;...", "ht:news_item_url": "https://tw.news.yahoo.com/%E5%A9%9A%E5%A7%BB%E7%88%86%E5%8D%B1%E6%A9%9F-%E5%A8%81%E5%BB%89-%E9%A9%9A%E4%BA%BA%E4%B9%8B%E8%88%89-%E9%81%AD%E5%8D%93%E5%90%9B%E6%BE%A4%E5%A4%A7%E7%BD%B5-%E4%BD%A0%E6%98%AF%E6%83%B3%E6%AD%BB%E5%97%8E-091003370.html", "ht:news_item_source": "Yahoo奇摩新聞"}]}, {"title": "ASML", "ht:approx_traffic": "2,000+", "description": null, "link": "https://trends.google.com.tw/trends/trendingsearches/daily?geo=TW#ASML", "pubDate": "Thu, 21 Jul 2022 11:00:00 +0800", "ht:picture": "https://t2.gstatic.com/images?q=tbn:ANd9GcRH9ehRB5XplSVyx_MFOYmYCDIevVqWt17kP2P8d1WSlZxyVsl2iugyMzYbtLMgQaEySpgr0bgI", "ht:picture_source": "中時新聞網", "ht:news_item": [{"ht:news_item_title": "《科技》ASML本季營收略降全年成長預期砍半", "ht:news_item_snippet": "【時報記者林資傑台北報導】半導體設備供應商艾司摩爾（ASML）公布2022年第二季財報，稅後淨利跳增至14.11億歐元，每股盈餘3.54歐元。展望第三季，公司預期營收將落&nbsp;...", "ht:news_item_url": "https://wantrich.chinatimes.com/news/20220721900327-420101", "ht:news_item_source": "中時新聞網"}, {"ht:news_item_title": "ASML 艾司摩爾(ASML) 財報分析2022 - StockFeel 股感", "ht:news_item_snippet": "ASML 全年成長預期腰斬！前景真的那麼糟？「晶片之母」艾司摩爾（ASML）盤前公布Q2 業績，營收54.31 億歐元，年增35%，雖然毛利率（49.1%）僅落在財測低標（49%～50%）&nbsp;...", "ht:news_item_url": "https://www.stockfeel.com.tw/asml-%E8%89%BE%E5%8F%B8%E6%91%A9%E7%88%BE-%E8%B2%A1%E5%A0%B1/", "ht:news_item_source": "StockFeel 股感"}]}, {"title": "姜丹尼爾", "ht:approx_traffic": "2,000+", "description": null, "link": "https://trends.google.com.tw/trends/trendingsearches/daily?geo=TW#%E5%A7%9C%E4%B8%B9%E5%B0%BC%E7%88%BE", "pubDate": "Thu, 21 Jul 2022 00:00:00 +0800", "ht:picture": "https://t1.gstatic.com/images?q=tbn:ANd9GcTrp_ZnLUaQ0_FN0zZyh-XrS_U-J2d0czms8L1NJvDAtfYEnVcWbilBwHvusLwrw30vsp_aCM2k", "ht:picture_source": "ETtoday星光雲", "ht:news_item": [{"ht:news_item_title": "「眼線濃《SWF》姐姐很可怕」掀性別對立姜丹尼爾遭罵爆道歉了", "ht:news_item_snippet": "南韓人氣男星姜丹尼爾曾是Wanna One一員，團體解散後，他積極發展個人事業，日前還接下大勢競賽節目《Street Woman Fighter》主持，知名度再往上攀，最近電視台推出&nbsp;...", "ht:news_item_url": "https://star.ettoday.net/news/2299027", "ht:news_item_source": "ETtoday星光雲"}, {"ht:news_item_title": "姜丹尼爾發文道歉！之前曾說：《SWF》的姐姐們很可怕，眼線畫 ...", "ht:news_item_snippet": "姜丹尼爾對《Street Woman Fighter》和《Street Man Fighter》參賽選手的言論引發了全韓網的熱議。 日前，姜丹尼爾通過Universe APP和粉絲們互動，期間他提到了自己&nbsp;...", "ht:news_item_url": "https://www.koreastardaily.com/tc/news/142423", "ht:news_item_source": "KSD 韓星網"}]}, {"title": "王凱", "ht:approx_traffic": "2,000+", "description": null, "link": "https://trends.google.com.tw/trends/trendingsearches/daily?geo=TW#%E7%8E%8B%E5%87%B1", "pubDate": "Thu, 21 Jul 2022 12:00:00 +0800", "ht:picture": "https://t3.gstatic.com/images?q=tbn:ANd9GcSnAWLWBm86KdEL7GZfCLt-P903jUY6VuIlzeLpNEmDpq-0umSnGiX7QhvO481C2HE2U0Psvpe1", "ht:picture_source": "Yahoo奇摩新聞", "ht:news_item": {"ht:news_item_title": "男星父3度中風「左半身癱瘓」逝世！王凱悲喊：不痛了", "ht:news_item_snippet": "39歲男星王凱演過偶像劇《薰衣草》、八點檔《雨後驕陽》、《多情城市》等經典作品，有「本土劇男神」的美稱。怎料，王凱近日悲曝噩耗，爸爸曾三度中風左半身癱瘓，&nbsp;...", "ht:news_item_url": "https://tw.news.yahoo.com/%E7%94%B7%E6%98%9F%E7%88%B63%E5%BA%A6%E4%B8%AD%E9%A2%A8-%E5%B7%A6%E5%8D%8A%E8%BA%AB%E7%99%B1%E7%98%93-%E9%80%9D%E4%B8%96-%E7%8E%8B%E5%87%B1%E6%82%B2%E5%96%8A-%E4%B8%8D%E7%97%9B%E4%BA%86-122219599.html", "ht:news_item_source": "Yahoo奇摩新聞"}}, {"title": "南山人壽", "ht:approx_traffic": "200,000+", "description": "潤泰新, 潤泰全, 潤泰, 寶成, 南山, 9945, 南山人壽股價, 2915, 潤泰集團, 潤泰新新聞, 潤泰全跌停, 尹衍樑, 潤泰新股價, 南山人壽淨值", "link": "https://trends.google.com.tw/trends/trendingsearches/daily?geo=TW#%E5%8D%97%E5%B1%B1%E4%BA%BA%E5%A3%BD", "pubDate": "Wed, 20 Jul 2022 11:00:00 +0800", "ht:picture": "https://t3.gstatic.com/images?q=tbn:ANd9GcTBTHojVAf3E6s8RghohpkdnKCKVxggBgwlWkDuqqoL-xwUt53ss-qjWdvjsGcK9a-mkhG3PsjF", "ht:picture_source": "經理人月刊", "ht:news_item": [{"ht:news_item_title": "南山人壽淨值大減，3家公司有危機？潤泰全、潤泰新、寶成深夜重訊 ...", "ht:news_item_snippet": "潤泰全指出，受利率變動影響，造成第一季其他權益因認列採權益法之關聯企業金融資產評價，減少約529 億元，5-6 月美國聯準會又接續升息5 碼，對金融資產可預期也會造成波動&nbsp;...", "ht:news_item_url": "https://www.managertoday.com.tw/articles/view/65467", "ht:news_item_source": "經理人月刊"}, {"ht:news_item_title": "淨值縮水拖累大股東潤泰？ 南山人壽提3點澄清：財務穩健", "ht:news_item_snippet": "今年因為俄烏戰爭造成能源、原物料等價格上揚，通貨膨脹問題更形嚴重，美國聯準會上半年升息6碼（1碼是0.25百分點），債券殖利率先行彈升反應升息，因此造成壽險公司手中&nbsp;...", "ht:news_item_url": "https://tw.news.yahoo.com/%E6%B7%A8%E5%80%BC%E7%B8%AE%E6%B0%B4%E6%8B%96%E7%B4%AF%E5%A4%A7%E8%82%A1%E6%9D%B1%E6%BD%A4%E6%B3%B0-%E5%8D%97%E5%B1%B1%E4%BA%BA%E5%A3%BD%E6%8F%903%E9%BB%9E%E6%BE%84%E6%B8%85-%E8%B2%A1%E5%8B%99%E7%A9%A9%E5%81%A5-231451826.html", "ht:news_item_source": "Yahoo奇摩新聞"}]}, {"title": "第四劑預約", "ht:approx_traffic": "50,000+", "description": "第四劑, 疫苗預約, 疫苗第四劑, 第四劑疫苗, 次世代疫苗, 台北市疫苗預約, 疫苗第四劑預約, 50歲第四劑預約", "link": "https://trends.google.com.tw/trends/trendingsearches/daily?geo=TW#%E7%AC%AC%E5%9B%9B%E5%8A%91%E9%A0%90%E7%B4%84", "pubDate": "Wed, 20 Jul 2022 17:00:00 +0800", "ht:picture": "https://t0.gstatic.com/images?q=tbn:ANd9GcQJ2SGBnWiXAWDMYyGQBGB8OjvuqL19-EWuiUC7eR1130xWbQWigjSnMfDuB0mQP7eGZq1YRMm-", "ht:picture_source": "中時新聞網", "ht:news_item": [{"ht:news_item_title": "50歲以上打第四劑北巿今、明開放上網預約", "ht:news_item_snippet": "中央疫情指揮中心指揮官王必勝昨宣布，22日起提供50歲以上成人接種第四劑疫苗，只要距離接種第三劑間隔5個月以上，或確診超過3個月皆可接種，台北市長柯文哲今上午出席&nbsp;...", "ht:news_item_url": "https://www.chinatimes.com/realtimenews/20220721002129-260405", "ht:news_item_source": "中時新聞網"}, {"ht:news_item_title": "第4劑下修至50歲！台大醫曝「4類人」快打：其他人可等次世代疫苗", "ht:news_item_snippet": "李建璋透露，現在若接種第四劑疫苗，那次世代疫苗開打時短時間內就不能施打，因為第五劑疫苗還沒有大規模臨床試驗，無法評估風險，因此不急著出國、不會接觸大量人群的民眾&nbsp;...", "ht:news_item_url": "https://www.ettoday.net/news/20220720/2298735.htm", "ht:news_item_source": "ETtoday"}]}, {"title": "千千", "ht:approx_traffic": "20,000+", "description": "千千結婚", "link": "https://trends.google.com.tw/trends/trendingsearches/daily?geo=TW#%E5%8D%83%E5%8D%83", "pubDate": "Wed, 20 Jul 2022 09:00:00 +0800", "ht:picture": "https://t2.gstatic.com/images?q=tbn:ANd9GcRn2XGn9Lt4EUXTCdslK8ukqZBKF248LKvHHRCKwk6LvUSYB8G6Qikg2xOZKkg04JJkbgxlRVnA", "ht:picture_source": "Yahoo奇摩新聞", "ht:news_item": [{"ht:news_item_title": "只遇過他！千千曾自曝「穩交10年」", "ht:news_item_snippet": "美食YouTuber「千千」以大胃王聞名，清新脫俗的長相，搭配親切又豪邁說話方式和態度形象，擄獲不少目光，頻道至今也已有174萬訂閱，今（20）日她被爆出在2年前就已「秘&nbsp;...", "ht:news_item_url": "https://tw.news.yahoo.com/%E5%8F%AA%E9%81%87%E9%81%8E%E4%BB%96-%E5%8D%83%E5%8D%83%E6%9B%BE%E8%87%AA%E6%9B%9D-%E7%A9%A9%E4%BA%A410%E5%B9%B4-061534612.html", "ht:news_item_source": "Yahoo奇摩新聞"}, {"ht:news_item_title": "大胃王千千爆祕婚2年她跨海親回覆「25字藏玄機」", "ht:news_item_snippet": "大胃王YouTuber千千擁百萬訂閱，其亮麗外表加上親民作風吸引大票粉絲。不過近日她被爆料祕婚團隊攝影師，時間長達2年，讓不少粉絲驚訝。對此，遠在泰國的千千也跨海&nbsp;...", "ht:news_item_url": "https://www.mirrormedia.mg/story/20220720edi048/", "ht:news_item_source": "鏡週刊"}]}, {"title": "全明星運動會第四季", "ht:approx_traffic": "20,000+", "description": "全明星運動會", "link": "https://trends.google.com.tw/trends/trendingsearches/daily?geo=TW#%E5%85%A8%E6%98%8E%E6%98%9F%E9%81%8B%E5%8B%95%E6%9C%83%E7%AC%AC%E5%9B%9B%E5%AD%A3", "pubDate": "Wed, 20 Jul 2022 14:00:00 +0800", "ht:picture": "https://t1.gstatic.com/images?q=tbn:ANd9GcRTmpkQv94iBg_29rt6LFIyYl2eFC1knAJEfVbRPkk-VQs3H_GOEy1LHniEZzknxBUJkwoz9xQU", "ht:picture_source": "Marie Claire 美麗佳人", "ht:news_item": [{"ht:news_item_title": "《全明星運動會》第四季帥哥鮮肉選手齊聚！原子少年夏浦洋、林輝 ...", "ht:news_item_snippet": "《全明星運動會》第四季參賽名單出爐啦！這回除了新增郭泓志領軍的黃隊，參賽者當中還有近期人氣超旺的「原子少年」！", "ht:news_item_url": "https://www.marieclaire.com.tw/entertainment/news/67122", "ht:news_item_source": "Marie Claire 美麗佳人"}, {"ht:news_item_title": "《全明星運動會4》30位選手名單公開！翁滋蔓、《與惡》陳妤 ...", "ht:news_item_snippet": "《全明星運動會》第四季20日在桃園舉辦首映記者會，領隊錢薇娟、郭泓志、江宏傑帶著30名選手，首度正式在觀眾面前曝光。此次選手多有體育背景出身，其中選手陳妤過去曾&nbsp;...", "ht:news_item_url": "https://tw.news.yahoo.com/%E3%80%8A%E5%85%A8%E6%98%8E%E6%98%9F%E9%81%8B%E5%8B%95%E6%9C%83-4-%E3%80%8B-30-%E4%BD%8D%E9%81%B8%E6%89%8B%E5%90%8D%E5%96%AE%E5%85%AC%E9%96%8B%EF%BC%81-%E7%BF%81%E6%BB%8B%E8%94%93%E3%80%81%E3%80%8A%E8%88%87%E6%83%A1%E3%80%8B%E9%99%B3%E5%A6%A4%E3%80%81%E3%80%8A%E5%8E%9F%E5%AD%90%E3%80%8B%E5%A4%8F%E6%B5%A6%E6%B4%8B%E9%83%BD%E4%BE%86%E4%BA%86-054033150.html", "ht:news_item_source": "Yahoo奇摩新聞"}]}, {"title": "胡文英", "ht:approx_traffic": "20,000+", "description": null, "link": "https://trends.google.com.tw/trends/trendingsearches/daily?geo=TW#%E8%83%A1%E6%96%87%E8%8B%B1", "pubDate": "Wed, 20 Jul 2022 00:00:00 +0800", "ht:picture": "https://t1.gstatic.com/images?q=tbn:ANd9GcTO5SPGNU2UeXnjXhecutTMgPXGXwU8kuQHG1nu4Ph_05K2qdQ1Lns__EGT8NZO_QPSm-AMe99s", "ht:picture_source": "ETtoday星光雲", "ht:news_item": [{"ht:news_item_title": "56歲胡文英「爆乳裝+網襪」神凍齡！驚29歲鮮肉男追求：老娘都可以 ...", "ht:news_item_snippet": "演藝圈許多凍齡美女，小S主持的節目《小姐不熙娣》就邀請眾多凍齡女星分享自己的故事。其中56歲「美魔女」胡文英身穿爆乳裝搭配網襪造型現身，完全看不出年過半百，&nbsp;...", "ht:news_item_url": "https://star.ettoday.net/news/2298263", "ht:news_item_source": "ETtoday星光雲"}, {"ht:news_item_title": "被「小26歲鮮肉男」追求！56歲胡文英搖頭嘆：我小孩都快30了…", "ht:news_item_snippet": "實習記者黃翎妍／綜合報導. 演藝圈凍齡美魔女不少，保養得宜的她們，臉上看不出歲月的痕跡。小S所主持的節目《小姐不熙娣》近日邀請到許多凍齡美女來分享有趣故事，&nbsp;...", "ht:news_item_url": "https://tw.news.yahoo.com/%E8%A2%AB-%E5%B0%8F26%E6%AD%B2%E9%AE%AE%E8%82%89%E7%94%B7-%E8%BF%BD%E6%B1%82-56%E6%AD%B2%E8%83%A1%E6%96%87%E8%8B%B1%E6%90%96%E9%A0%AD%E5%98%86-%E6%88%91%E5%B0%8F%E5%AD%A9%E9%83%BD%E5%BF%AB30%E4%BA%86-100946378.html", "ht:news_item_source": "Yahoo奇摩新聞"}]}, {"title": "金佳藍", "ht:approx_traffic": "20,000+", "description": "金佳覽, le sserafim", "link": "https://trends.google.com.tw/trends/trendingsearches/daily?geo=TW#%E9%87%91%E4%BD%B3%E8%97%8D", "pubDate": "Wed, 20 Jul 2022 12:00:00 +0800", "ht:picture": "https://t0.gstatic.com/images?q=tbn:ANd9GcScAj-Ax3j-A-3wLoazPXWR_j6ZM5BxJtoN4zeaBpqgHBcHpmlXtFeOLqaYqJDKqkxK1qE1Qdz1", "ht:picture_source": "Yahoo奇摩新聞", "ht:news_item": [{"ht:news_item_title": "「校園霸凌」讓金佳藍合同終止LE SSERAFIM確定「5人組」", "ht:news_item_snippet": "[周刊王CTWANT] 南韓6人女團LE.", "ht:news_item_url": "https://tw.news.yahoo.com/%E6%A0%A1%E5%9C%92%E9%9C%B8%E5%87%8C-%E8%AE%93%E9%87%91%E4%BD%B3%E8%97%8D%E5%90%88%E5%90%8C%E7%B5%82%E6%AD%A2-le-sserafim%E7%A2%BA%E5%AE%9A-5%E4%BA%BA%E7%B5%84-065023868.html", "ht:news_item_source": "Yahoo奇摩新聞"}, {"ht:news_item_title": "金佳藍涉校園欺凌退出LE SSERAFIM - 20220721 - 娛樂", "ht:news_item_snippet": "【明報專訊】由日韓限定女團IZ*ONE前成員宮脇咲良及金采源領軍的6人女子組合LE SSERAFIM，今年5月初推出首張迷你專輯《FEARLESS》，迅即打破韓國女團出道唱片最高銷售&nbsp;...", "ht:news_item_url": "https://news.mingpao.com/pns/%E5%A8%9B%E6%A8%82/article/20220721/s00016/1658340378359/%E9%87%91%E4%BD%B3%E8%97%8D%E6%B6%89%E6%A0%A1%E5%9C%92%E6%AC%BA%E5%87%8C%E9%80%80%E5%87%BAle-sserafim", "ht:news_item_source": "明報新聞網"}]}, {"title": "沉香如屑", "ht:approx_traffic": "10,000+", "description": "沈香如屑", "link": "https://trends.google.com.tw/trends/trendingsearches/daily?geo=TW#%E6%B2%89%E9%A6%99%E5%A6%82%E5%B1%91", "pubDate": "Wed, 20 Jul 2022 20:00:00 +0800", "ht:picture": "https://t3.gstatic.com/images?q=tbn:ANd9GcRu_-kH0PJKPu2r4aBK3VhePVd0FEL-CXUbszyrcaeAE_eRjVKLRXGDbXVFju7LMJp_1niqjukA4Q", "ht:picture_source": "臺灣新浪網", "ht:news_item": [{"ht:news_item_title": "楊紫成毅主演《沉香如屑》「無預警」上線優酷", "ht:news_item_snippet": "新京報訊7月20日，由楊紫、成毅主演的仙俠劇《沉香如屑》在沒有提前預告的情況「無預警」上線優酷，目前普通會員看兩集，VIP會員看5集。《沉香如屑》改編自...", "ht:news_item_url": "https://news.sina.com.tw/article/20220720/42236822.html", "ht:news_item_source": "臺灣新浪網"}, {"ht:news_item_title": "【年度劇王來襲】楊紫、成毅新戲《沉香如屑》空降播出兩人重返 ...", "ht:news_item_snippet": "楊紫、成毅主演的仙俠劇《沉香如屑》自6月起就被優酷列入待播清單，更被看好是暑假黃金檔最有話題的作品，...", "ht:news_item_url": "https://www.upmedia.mg/news_info.php?Type=196&SerialNo=149680", "ht:news_item_source": "上報"}]}, {"title": "蓮池潭", "ht:approx_traffic": "10,000+", "description": "蓮池潭溺水", "link": "https://trends.google.com.tw/trends/trendingsearches/daily?geo=TW#%E8%93%AE%E6%B1%A0%E6%BD%AD", "pubDate": "Wed, 20 Jul 2022 18:00:00 +0800", "ht:picture": "https://t2.gstatic.com/images?q=tbn:ANd9GcR_8EG3YgSz0hzHPMnv2apbvu2Vrr8O4gh-BXADqN6clqdDENlz7iPTPmlmCPDVg-9jzVa-0ZH-", "ht:picture_source": "上報", "ht:news_item": [{"ht:news_item_title": "高雄蓮池潭風帆翻覆意外失蹤教練遺體尋獲--上報", "ht:news_item_snippet": "高雄蓮池潭20日發生一名9歲男童上風帆課時，因船隻翻覆和練雙雙落水意外，男童救起時已無呼吸心跳，教練失...", "ht:news_item_url": "https://www.upmedia.mg/news_info.php?Type=24&SerialNo=149760", "ht:news_item_source": "上報"}, {"ht:news_item_title": "蓮池潭帆船翻覆1男童不治失蹤教練清晨尋獲已明顯死亡", "ht:news_item_snippet": "高雄市蓮池潭昨天發生溺水意外，蔡姓教練和王姓男童進行帆船訓練課，船隻因不明原因翻覆，王童送醫不治，失蹤的教練經過漏夜搜尋後，今天清晨尋獲，但已明顯死亡。", "ht:news_item_url": "https://tw.news.yahoo.com/%E8%93%AE%E6%B1%A0%E6%BD%AD%E5%B8%86%E8%88%B9%E7%BF%BB%E8%A6%86%E7%94%B7%E7%AB%A5%E4%B8%8D%E6%B2%BB-%E5%A4%B1%E8%B9%A4%E6%95%99%E7%B7%B4%E6%B8%85%E6%99%A8%E5%B0%8B%E7%8D%B2%E5%B7%B2%E6%98%8E%E9%A1%AF%E6%AD%BB%E4%BA%A1-010420090.html", "ht:news_item_source": "Yahoo奇摩新聞"}]}]}}}